keepkey-6.3.1.data/scripts/keepkeyctl
keepkeylib/__init__.py
keepkeylib/ckd_public.py
keepkeylib/client.py
keepkeylib/cosmos.py
keepkeylib/debuglink.py
keepkeylib/eos.py
keepkeylib/exchange.py
keepkeylib/exchange_pb2.py
keepkeylib/filecache.py
keepkeylib/mapping.py
keepkeylib/messages_cosmos_pb2.py
keepkeylib/messages_eos_pb2.py
keepkeylib/messages_nano_pb2.py
keepkeylib/messages_pb2.py
keepkeylib/messages_ripple_pb2.py
keepkeylib/nano.py
keepkeylib/protobuf.py
keepkeylib/protobuf_json.py
keepkeylib/ripple.py
keepkeylib/tools.py
keepkeylib/transport.py
keepkeylib/transport_fake.py
keepkeylib/transport_hid.py
keepkeylib/transport_pipe.py
keepkeylib/transport_serial.py
keepkeylib/transport_socket.py
keepkeylib/transport_udp.py
keepkeylib/transport_webusb.py
keepkeylib/tx_api.py
keepkeylib/types_pb2.py
keepkeylib/eth/__init__.py
keepkeylib/eth/ethereum_tokens.py
keepkeylib/qt/__init__.py
keepkeylib/qt/pinmatrix.py
keepkey-6.3.1.dist-info/COPYING
keepkey-6.3.1.dist-info/METADATA
keepkey-6.3.1.dist-info/WHEEL
keepkey-6.3.1.dist-info/top_level.txt
keepkey-6.3.1.dist-info/RECORD
