Metadata-Version: 2.1
Name: keepkey
Version: 6.3.1
Summary: Python library for communicating with KeepKey Hardware Wallet
Home-page: https://github.com/keepkey/python-keepkey
Author: TREZOR and KeepKey
Author-email: support@keepkey.com
License: UNKNOWN
Platform: UNKNOWN
Classifier: License :: OSI Approved :: GNU Lesser General Public License v3 (LGPLv3)
Classifier: Operating System :: POSIX :: Linux
Classifier: Operating System :: Microsoft :: Windows
Classifier: Operating System :: MacOS :: MacOS X
Provides-Extra: ethereum
